zerodose/__init__.py
zerodose/__main__.py
zerodose/dataset.py
zerodose/inference.py
zerodose/models.py
zerodose/networks.py
zerodose/paths.py
zerodose/pipeline/__init__.py
zerodose/pipeline/abnormality.py
zerodose/pipeline/full.py
zerodose/pipeline/main.py
zerodose/pipeline/niftyreg.py
zerodose/pipeline/normalization.py
zerodose/pipeline/synthetization.py
zerodose/processing.py
zerodose/py.typed
zerodose/utils.py
zerodose/visualizations.py
zerodose-0.0.6.dist-info/LICENSE
zerodose-0.0.6.dist-info/METADATA
zerodose-0.0.6.dist-info/WHEEL
zerodose-0.0.6.dist-info/entry_points.txt
zerodose-0.0.6.dist-info/RECORD
