Metadata-Version: 2.1
Name: zerodose
Version: 0.0.6
Summary: Zerodose
Home-page: https://github.com/ChristianHinge/zerodose
License: MIT
Author: Christian Hinge
Author-email: christian.hinge@regionh.dk
Requires-Python: >=3.8,<3.11
Classifier: Development Status :: 1 - Planning
Classifier: License :: OSI Approved :: MIT License
Classifier: Programming Language :: Python :: 3
Classifier: Programming Language :: Python :: 3.8
Classifier: Programming Language :: Python :: 3.9
Classifier: Programming Language :: Python :: 3.10
Provides-Extra: plotting
Requires-Dist: click (>=8.0.1)
Requires-Dist: matplotlib (>=3.7.1,<4.0.0) ; extra == "plotting"
Requires-Dist: niftyreg (>=1.5.70rc1,<2.0.0)
Requires-Dist: opencv-python (>=4.7.0.72,<5.0.0.0) ; extra == "plotting"
Requires-Dist: torch (>=1.0.0)
Requires-Dist: torchio (>=0.18.0,<0.19.0)
Project-URL: Changelog, https://github.com/ChristianHinge/zerodose/releases
Project-URL: Documentation, https://zerodose.readthedocs.io
Project-URL: Repository, https://github.com/ChristianHinge/zerodose
